sonusai-1.1.0.dist-info/METADATA
sonusai-1.1.0.dist-info/WHEEL
sonusai-1.1.0.dist-info/entry_points.txt
sonusai/__init__.py
sonusai/aawscd_probwrite.py
sonusai/audiofe.py
sonusai/calc_metric_spenh.py
sonusai/config/__init__.py
sonusai/config/asr.py
sonusai/config/config.py
sonusai/config/config.yml
sonusai/config/constants.py
sonusai/config/ir.py
sonusai/config/ir_delay.py
sonusai/config/source.py
sonusai/config/spectral_masks.py
sonusai/config/truth.py
sonusai/constants.py
sonusai/data/__init__.py
sonusai/data/silero_vad_v5.1.jit
sonusai/data/silero_vad_v5.1.onnx
sonusai/data/speech_ma01_01.wav
sonusai/data/whitenoise.wav
sonusai/datatypes.py
sonusai/deprecated/gentcst.py
sonusai/deprecated/plot.py
sonusai/deprecated/tplot.py
sonusai/doc.py
sonusai/doc_strings/__init__.py
sonusai/doc_strings/doc_strings.py
sonusai/genft.py
sonusai/genmetrics.py
sonusai/genmix.py
sonusai/genmixdb.py
sonusai/ir_metric.py
sonusai/lsdb.py
sonusai/main.py
sonusai/metrics/__init__.py
sonusai/metrics/calc_audio_stats.py
sonusai/metrics/calc_class_weights.py
sonusai/metrics/calc_optimal_thresholds.py
sonusai/metrics/calc_pcm.py
sonusai/metrics/calc_pesq.py
sonusai/metrics/calc_phase_distance.py
sonusai/metrics/calc_sa_sdr.py
sonusai/metrics/calc_sample_weights.py
sonusai/metrics/calc_segsnr_f.py
sonusai/metrics/calc_speech.py
sonusai/metrics/calc_wer.py
sonusai/metrics/calc_wsdr.py
sonusai/metrics/calculate_metrics.py
sonusai/metrics/class_summary.py
sonusai/metrics/confusion_matrix_summary.py
sonusai/metrics/one_hot.py
sonusai/metrics/snr_summary.py
sonusai/metrics_summary.py
sonusai/mixture/__init__.py
sonusai/mixture/audio.py
sonusai/mixture/class_balancing.py
sonusai/mixture/constants.py
sonusai/mixture/data_io.py
sonusai/mixture/db.py
sonusai/mixture/db_datatypes.py
sonusai/mixture/effects.py
sonusai/mixture/feature.py
sonusai/mixture/generation.py
sonusai/mixture/helpers.py
sonusai/mixture/ir_effects.py
sonusai/mixture/log_duration_and_sizes.py
sonusai/mixture/mixdb.py
sonusai/mixture/pad_audio.py
sonusai/mixture/sox_effects.py
sonusai/mixture/sox_help.py
sonusai-1.1.0.dist-info/RECORD
